bda.plone.discount-2.0b1-py3.9-nspkg.pth
bda/plone/discount/__init__.py
bda/plone/discount/calculator.py
bda/plone/discount/configure.zcml
bda/plone/discount/i18n.sh
bda/plone/discount/interfaces.py
bda/plone/discount/permissions.py
bda/plone/discount/permissions.zcml
bda/plone/discount/profiles.zcml
bda/plone/discount/settings.py
bda/plone/discount/setuphandlers.py
bda/plone/discount/upgrades.zcml
bda/plone/discount/browser/__init__.py
bda/plone/discount/browser/actions.py
bda/plone/discount/browser/configure.zcml
bda/plone/discount/browser/discount.yaml
bda/plone/discount/browser/discount_view.pt
bda/plone/discount/browser/forms.py
bda/plone/discount/browser/general_header.pt
bda/plone/discount/browser/group_header.pt
bda/plone/discount/browser/user_header.pt
bda/plone/discount/browser/views.py
bda/plone/discount/browser/static/discount.css
bda/plone/discount/browser/static/discount.css.map
bda/plone/discount/browser/static/discount.js
bda/plone/discount/browser/static/discount.min.css
bda/plone/discount/locales/bda.plone.discount.pot
bda/plone/discount/locales/manual.pot
bda/plone/discount/locales/de/LC_MESSAGES/bda.plone.discount.po
bda/plone/discount/locales/en/LC_MESSAGES/bda.plone.discount.po
bda/plone/discount/locales/fr/LC_MESSAGES/bda.plone.discount.po
bda/plone/discount/locales/it/LC_MESSAGES/bda.plone.discount.po
bda/plone/discount/locales/no/LC_MESSAGES/bda.plone.discount.po
bda/plone/discount/profiles/default/actions.xml
bda/plone/discount/profiles/default/browserlayer.xml
bda/plone/discount/profiles/default/metadata.xml
bda/plone/discount/profiles/default/registry.xml
bda/plone/discount/profiles/default/rolemap.xml
bda/plone/discount/profiles/uninstall/actions.xml
bda/plone/discount/profiles/uninstall/browserlayer.xml
bda/plone/discount/profiles/uninstall/registry.xml
bda/plone/discount/tests/__init__.py
bda/plone/discount/tests/calculator.rst
bda/plone/discount/tests/settings.rst
bda/plone/discount/tests/test_discount.py
bda.plone.discount-2.0b1.dist-info/LICENSE.rst
bda.plone.discount-2.0b1.dist-info/LICENSE_GPL.rst
bda.plone.discount-2.0b1.dist-info/METADATA
bda.plone.discount-2.0b1.dist-info/WHEEL
bda.plone.discount-2.0b1.dist-info/namespace_packages.txt
bda.plone.discount-2.0b1.dist-info/top_level.txt
bda.plone.discount-2.0b1.dist-info/RECORD
