Metadata-Version: 2.1
Name: bda.plone.discount
Version: 2.0b1
Summary: Discounting Information for Content Items
Author: BlueDynamics Alliance
Author-email: dev@bluedynamics.com
License: GNU General Public Licence
Classifier: Framework :: Plone
Classifier: Framework :: Plone :: 6.0
Classifier: Framework :: Plone :: Addon
Classifier: Framework :: Zope
Classifier: Framework :: Zope :: 5
Classifier: License :: OSI Approved :: GNU General Public License (GPL)
Classifier: Programming Language :: Python
Classifier: Programming Language :: Python :: 3.7
Classifier: Programming Language :: Python :: 3.8
Classifier: Programming Language :: Python :: 3.9
Classifier: Programming Language :: Python :: 3.10
Classifier: Topic :: Software Development :: Libraries :: Python Modules
License-File: LICENSE.rst
License-File: LICENSE_GPL.rst
Requires-Dist: setuptools
Requires-Dist: Plone
Requires-Dist: souper.plone
Requires-Dist: yafowil.plone
Requires-Dist: yafowil.widget.autocomplete
Requires-Dist: yafowil.widget.array
Requires-Dist: bda.plone.cart
Provides-Extra: test
Requires-Dist: plone.app.testing ; extra == 'test'
Requires-Dist: mock ; extra == 'test'
